app/__init__.py
app/__main__.py
app/db_create.py
app/fastapi_run.py
app/main.py
app/comm/__init__.py
app/comm/config.py
app/comm/utils.py
app/db/__init__.py
app/db/database.py
app/db/models/__init__.py
app/db/models/project_info.py
app/exam/__init__.py
app/exceptions/__init__.py
app/exceptions/api.py
app/exceptions/crud.py
app/model/__init__.py
app/model/base.py
app/model/sample/__init__.py
app/model/sample/sample_model.py
app/router/__init__.py
app/router/sample_router.py
fastapi_hcytools/__init__.py
fastapi_hcytools/__main__.py
fastapi_hcytools/db_create.py
fastapi_hcytools/fastapi_run.py
fastapi_hcytools/main.py
fastapi_hcytools/comm/__init__.py
fastapi_hcytools/comm/config.py
fastapi_hcytools/comm/utils.py
fastapi_hcytools/db/__init__.py
fastapi_hcytools/db/database.py
fastapi_hcytools/db/models/__init__.py
fastapi_hcytools/db/models/project_info.py
fastapi_hcytools/exam/__init__.py
fastapi_hcytools/exceptions/__init__.py
fastapi_hcytools/exceptions/api.py
fastapi_hcytools/exceptions/crud.py
fastapi_hcytools/model/__init__.py
fastapi_hcytools/model/base.py
fastapi_hcytools/model/sample/__init__.py
fastapi_hcytools/model/sample/sample_model.py
fastapi_hcytools/router/__init__.py
fastapi_hcytools/router/sample_router.py
fastapi_hcytools-1.1.3.dist-info/METADATA
fastapi_hcytools-1.1.3.dist-info/WHEEL
fastapi_hcytools-1.1.3.dist-info/top_level.txt
fastapi_hcytools-1.1.3.dist-info/RECORD
